{
  "id": "how-microsoft-engineers-build-enterprise-blockchain-apps-on-ethereum-networks",
  "sourceId": "how-microsoft-engineers-build-enterprise-blockchain-apps-on-ethereum-networks",
  "eventId": "devcon-5",
  "title": "How Microsoft engineers build enterprise Blockchain apps on Ethereum Networks",
  "description": "Enterprise Blockchain applications have different constraints and challenges to ones on public networks. Come see how Microsoft engineers architect based on market segment (B2B / B2C), and use serverless compute to integrate systems onto Ethereum networks. This will be a demo heavy presentation showing real world engineering used at top enterprises, such as DevOps, unit testing, serverless compute, VS Code scaffolding.",
  "track": "Developer Infrastructure",
  "type": "Breakout",
  "expertise": "Beginner",
  "tags": [
    "Developer Infrastructure"
  ],
  "speakers": [
    "david-burela",
    "whitney-griffith"
  ],
  "sources_youtubeId": "UCpg4kz4GiE",
  "sources_ipfsHash": "QmbZFaK7VcYgSxmV9kbJ67NK6CQmyv9nB4SEGKajBsrwbM",
  "sources_swarmHash": "c2ea400e9ce325601b53dad81906dc78f04c0d0eae776287947a3e60614db107",
  "duration": 3457,
  "language": "en"
}