{
  "id": "privacy-in-ethereum",
  "sourceId": "privacy-in-ethereum",
  "eventId": "devcon-5",
  "title": "Privacy in Ethereum",
  "description": "From mixer to anonDAO, anonSocial media to journalism under authoritarian regimes ethereum offers ways to provide privacy to people who need it most. Come hear what we have done and what we want to do. How *YOU* can help us move forward.",
  "track": "Privacy",
  "type": "Talk",
  "expertise": "Intermediate",
  "tags": [
    "Privacy",
    "barry",
    "whitehat",
    "security",
    "technical"
  ],
  "speakers": [
    "barry-whitehat"
  ],
  "sources_youtubeId": "zBUo7G95wYE",
  "sources_ipfsHash": "QmW4588uWqyVvtcnN7eZH7i37hpNTmYNh8NTpc8MTjsXQW",
  "sources_swarmHash": "1bd3d489f8357080fc18dd497ff9c13215fb3dc7ad2e3ffa70b75c309c7516a0",
  "duration": 1264,
  "language": "en"
}