{
  "id": "decentralize-democratize-or-die",
  "sourceId": "decentralize-democratize-or-die",
  "eventId": "devcon-4",
  "title": "Decentralize, Democratize, or Die",
  "description": "Cory Doctorow from the Electronic Frontier Foundation discusses the \"crypto wars\" & where we go from here.",
  "track": "Governance & Coordination",
  "type": "Talk",
  "expertise": "Beginner",
  "tags": [
    "Governance & Coordination",
    "democracy"
  ],
  "speakers": [
    "cory-doctorow"
  ],
  "sources_youtubeId": "fbvEerKOcYs",
  "sources_ipfsHash": "QmaRpPXyc1VhwFGdXjnCiNumCyZS9SUXyzAkoYHQN38DU3",
  "sources_swarmHash": "100690990e02bc67e3acf2fd224beeea09df57d4825ef8c669d4ca762e0e1295",
  "duration": 3028,
  "language": "en"
}