{
  "id": "how-will-nations-remain-relevant-in-the-21st-century",
  "sourceId": "how-will-nations-remain-relevant-in-the-21st-century",
  "eventId": "devcon-4",
  "title": "How will nations remain relevant in the 21st century?",
  "description": "Kaspar Korjus discusses how nations will remain relevant in the 21st century.",
  "track": "Governance & Coordination",
  "type": "Talk",
  "expertise": "Beginner",
  "tags": [
    "Governance & Coordination",
    "global",
    "economy"
  ],
  "speakers": [
    "kaspar-korjus"
  ],
  "sources_youtubeId": "61YRbA9gWe8",
  "sources_ipfsHash": "QmW8YYTyKqpARTQUcKHj9KiMvirvj5CNjrGsFPdnDfayYg",
  "sources_swarmHash": "dc8314cee5712127f2cca3fbc5896899bdf7715b0009498691dfc3a93d09e4f0",
  "duration": 1417,
  "language": "en"
}