{
  "id": "swarm",
  "sourceId": "swarm",
  "eventId": "devcon-1",
  "title": "Swarm",
  "description": "Ethereum's Dr. Daniel Nagy and Viktor Tron present on Swarm, the decentralised, incentivised file storage system.",
  "track": "Developer Infrastructure",
  "type": "Talk",
  "expertise": "Advanced",
  "tags": [
    "Developer Infrastructure",
    "incentives",
    "file",
    "storage",
    "content",
    "distribution",
    "redundancy",
    "integrity",
    "chunk",
    "devp2p",
    "bzz",
    "insurance",
    "layers",
    "dapp",
    "structure",
    "updates",
    "demo"
  ],
  "speakers": [
    "daniel-nagy",
    "viktor-tron"
  ],
  "sources_youtubeId": "VOC45AgZG5Q",
  "sources_ipfsHash": "QmQjgP9GvcjqMhP7yUtVX1edG5MJYAPtAaVQUhzgmNAvRJ",
  "sources_swarmHash": "f0ca93db45942b243e28dc230ad438842f8954bd6a7a7ca00ba05cce72663648",
  "duration": 1711,
  "language": "en"
}