{
  "id": "tokens",
  "sourceId": "tokens",
  "eventId": "devcon-1",
  "title": "Tokens",
  "description": "Simon de la Rouviere of ConsenSys presents on tokens and standards on the Ethereum blockchain.",
  "track": "Developer Infrastructure",
  "type": "Talk",
  "expertise": "Intermediate",
  "tags": [
    "Developer Infrastructure"
  ],
  "speakers": [
    "simon-de-la-rouviere"
  ],
  "sources_youtubeId": "kE5oGw8oKsY",
  "sources_ipfsHash": "QmS6vqNGZX9eRDauaPaZNN2L69xAvLmhKhs6X9UYHB9hWA",
  "sources_swarmHash": "8ead412606366593919d3e3e33598349d1e15c01f908ff6be24108708bcb4dd5",
  "duration": 1007,
  "language": "en"
}