{
  "id": "ecosystem-support-program-day",
  "sourceId": "PTRGTA",
  "eventId": "devcon-6",
  "title": "Ecosystem Support Program Day",
  "description": "ESP Day is a full day of talks and panel discussions with the purpose of exploring topics or projects pertinent to ecosystem development while highlighting the EF's grantees. Join us for wide-ranging conversations on building a post-Merge world, supporting education initiatives across cultures to reach our next billion, game development to achieve ZK scaling, and more!",
  "track": "Opportunity & Global Impact",
  "type": "Workshop",
  "expertise": "Beginner",
  "tags": [
    "Opportunity & Global Impact",
    "ecosystem",
    "support"
  ],
  "speakers": [
    "monet-du-plessis",
    "madison-adams"
  ],
  "resources_slides": "/resources/6/ecosystem-support-program-day.pdf",
  "sources_youtubeId": "EVrQy03WekI",
  "duration": 2135,
  "language": "en"
}