{
  "id": "hardhat-and-nomic-foundation-the-creation-of-an-ethereum-non-profit",
  "sourceId": "XYFHFZ",
  "eventId": "devcon-6",
  "title": "Hardhat & Nomic Foundation: the creation of an Ethereum non-profit",
  "description": "Learn about the creation of the Nomic Foundation and what's coming next from the creators of Hardhat.",
  "track": "Developer Infrastructure",
  "type": "Talk",
  "expertise": "Beginner",
  "tags": [
    "Developer Infrastructure",
    "developer experience",
    "hardhat",
    "nomic"
  ],
  "speakers": [
    "franco-zeoli"
  ],
  "resources_slides": "/resources/6/hardhat-and-nomic-foundation-the-creation-of-an-ethereum-non-profit.pdf",
  "slot_start": 1665671400000,
  "slot_end": 1665673200000,
  "slot_roomId": "talk-1",
  "sources_youtubeId": "C9jtgs0vOI4",
  "sources_swarmHash": "a4e06a690d90f3ab9b624a157bca1faebea577eee26ec9462fc8ae416d0a4e51",
  "duration": 1320,
  "language": "en"
}