{
  "id": "promoting-small-and-independent-stakers-qanda-with-the-ethereum-staking-protocols",
  "sourceId": "STRWX7",
  "eventId": "devcon-6",
  "title": "Promoting Small and Independent Stakers: Q&A with the Ethereum Staking Protocols",
  "description": "The Node Operator Association presents a roundtable discussion on promoting small and independent professional stakers. Topics include operator qualifications, application processes, costs, risks, each platform's unique advantages, and their vision for the future of Ethereum staking.\nPanelists:  Darren Langley (Rocket Pool) Vasiliy Shapovalov (Lido) Oisin Kyne (Obol) Jordan Sutcliffe (Stakewise) Ariel Zimroni (SSV Network)",
  "track": "Staking & Validator Experience",
  "type": "Panel",
  "expertise": "",
  "tags": [
    "Staking & Validator Experience",
    "SaaS",
    "Staking",
    "Protocols"
  ],
  "speakers": [
    "ken-smith",
    "oisin-kyne",
    "darren-langley",
    "mike-leach",
    "ariel-zimroni",
    "jordan-sutcliffe",
    "vasiliy-shapovalov"
  ],
  "slot_start": 1665504000000,
  "slot_end": 1665507000000,
  "slot_roomId": "talk-4",
  "sources_youtubeId": "Exh-hQOV8kE",
  "sources_swarmHash": "ad8496eda794da44c27917d20d1e4d02bc8cc83bb65c661fab8049af110edf77",
  "duration": 694,
  "language": "en"
}