{
  "id": "erc-identity",
  "sourceId": "erc-identity",
  "eventId": "devcon-3",
  "title": "ERC Identity",
  "description": "Fabian Vogelsteller (author of ERC20) will be talking about his new work on standard functions for a unique identity for humans and machines.",
  "track": "Developer Infrastructure",
  "type": "Talk",
  "expertise": "Intermediate",
  "tags": [
    "Developer Infrastructure"
  ],
  "speakers": [
    "fabian-vogelsteller"
  ],
  "sources_youtubeId": "pkwYVagytuA",
  "sources_ipfsHash": "QmYj1sE23xwPzYB15NuvVaF4vmx8dSqnA7zhP1K3zqypAs",
  "sources_swarmHash": "eeef5c34a45c758e086e1e7f65b090f6328c9c359a7d80e20d247c32e895265c",
  "duration": 1302,
  "language": "en"
}